web_list_info_spider/__init__.py
web_list_info_spider/__main__.py
web_list_info_spider/main.py
web_list_info_spider-0.8.dist-info/METADATA
web_list_info_spider-0.8.dist-info/WHEEL
web_list_info_spider-0.8.dist-info/entry_points.txt
web_list_info_spider-0.8.dist-info/top_level.txt
web_list_info_spider-0.8.dist-info/RECORD
