Metadata-Version: 2.1
Name: web-list-info-spider
Version: 0.8
Summary: UNKNOWN
Home-page: UNKNOWN
License: UNKNOWN
Platform: UNKNOWN
Requires-Dist: pandas
Requires-Dist: requests
Requires-Dist: PySide6
